black/__init__.py
black/__main__.py
blib2to3/__init__.py
blib2to3/pygram.py
blib2to3/pytree.py
blib2to3/pgen2/__init__.py
blib2to3/pgen2/conv.py
blib2to3/pgen2/driver.py
blib2to3/pgen2/grammar.py
blib2to3/pgen2/literals.py
blib2to3/pgen2/parse.py
blib2to3/pgen2/pgen.py
blib2to3/pgen2/token.py
blib2to3/pgen2/tokenize.py
mo_black-22.364.23070.dist-info/LICENSE
mo_black-22.364.23070.dist-info/METADATA
mo_black-22.364.23070.dist-info/WHEEL
mo_black-22.364.23070.dist-info/entry_points.txt
mo_black-22.364.23070.dist-info/top_level.txt
mo_black-22.364.23070.dist-info/RECORD
