Metadata-Version: 2.1
Name: mo-black
Version: 22.364.23070
Summary: More Black! Denser Black formatting
Home-page: https://github.com/klahnakoski/mo-black
Author: Various
Author-email: kyle@lahnakoski.com
License: MIT
Classifier: Development Status :: 4 - Beta
Classifier: Environment :: Console
Classifier: Intended Audience :: Developers
Classifier: License :: OSI Approved :: MIT License
Classifier: Operating System :: OS Independent
Classifier: Programming Language :: Python
Classifier: Programming Language :: Python :: 3.7
Classifier: Topic :: Software Development :: Libraries :: Python Modules
Classifier: Topic :: Software Development :: Quality Assurance
License-File: LICENSE
Requires-Dist: appdirs (==1.4.4)
Requires-Dist: click (==8.1.3)
Requires-Dist: colorama (==0.4.5)
Requires-Dist: importlib-metadata (==4.12.0)
Requires-Dist: mypy-extensions (==0.4.3)
Requires-Dist: pathspec (==0.6)
Requires-Dist: regex (==2020.1.8)
Requires-Dist: toml (==0.9.4)
Requires-Dist: typed-ast (==1.4.0)
Requires-Dist: typing-extensions (==4.3.0)
Requires-Dist: zipp (==3.8.1)
Provides-Extra: tests
Requires-Dist: mo-logs ; extra == 'tests'
Requires-Dist: pip-tools ; extra == 'tests'
